CHANGELOG.md
irrCAC/__init__.py
irrCAC/benchmark.py
irrCAC/datasets.py
irrCAC/raw.py
irrCAC/table.py
irrCAC/weights.py
irrcac-0.4.3.dist-info/METADATA
irrcac-0.4.3.dist-info/WHEEL
irrcac-0.4.3.dist-info/RECORD
