Metadata-Version: 2.1
Name: irrCAC
Version: 0.4.3
Summary: Degree of agreement among raters.
Home-page: https://github.com/afergadis/irrCAC
Keywords: Chance-corrected agreement coefficients,Inter-rater reliability,Inter-annotator agreement
Author: Aris Fergadis
Requires-Python: >=3.9,<4.0
Classifier: Programming Language :: Python :: 3
Classifier: Programming Language :: Python :: 3.9
Classifier: Programming Language :: Python :: 3.10
Classifier: Programming Language :: Python :: 3.11
Classifier: Programming Language :: Python :: 3.12
Requires-Dist: coverage (>=6.2,<7.0)
Requires-Dist: pandas (>=2.2.2,<3.0.0)
Requires-Dist: scipy (==1.12.0)
Project-URL: Repository, https://github.com/afergadis/irrCAC
